README.rst
setup.py
apptemplates/__init__.py
django_apptemplates2.egg-info/PKG-INFO
django_apptemplates2.egg-info/SOURCES.txt
django_apptemplates2.egg-info/dependency_links.txt
django_apptemplates2.egg-info/entry_points.txt
django_apptemplates2.egg-info/not-zip-safe
django_apptemplates2.egg-info/top_level.txt