Metadata-Version: 1.1
Name: django-apptemplates2
Version: 0.2a0
Summary: Django template loader that allows you to load template from a specific application
Home-page: UNKNOWN
Author: Konrad Wojas
Author-email: konrad.wojas@jibecompany.com
License: UNKNOWN
Keywords: django templates
Platform: UNKNOWN
Classifier: Framework :: Django
Classifier: Intended Audience :: Developers
Classifier: License :: OSI Approved :: MIT License
